hakisto/.git
hakisto/README.md
hakisto/__init__.py
hakisto/_base.py
hakisto/_logger.py
hakisto/_logger_globals.py
hakisto/click/__init__.py
hakisto/click/_click.py
hakisto/click/file.py
hakisto/click/inline_location.py
hakisto/click/severity.py
hakisto/click/short_trace.py
hakisto/click/use_color.py
hakisto/click.py
hakisto/colors.py
hakisto/demo.py
hakisto/file_handler.py
hakisto/handler.py
hakisto/handler_settings.py
hakisto/indented_renderer.py
hakisto/legacy/__init__.py
hakisto/legacy/_logger.py
hakisto/logger.py
hakisto/severity.py
hakisto/single_line_renderer.py
hakisto/stderr_handler.py
hakisto/stream.py
hakisto/subject.py
hakisto/topic.py
hakisto-0.4.1.dist-info/LICENSE.md
hakisto-0.4.1.dist-info/METADATA
hakisto-0.4.1.dist-info/WHEEL
hakisto-0.4.1.dist-info/entry_points.txt
hakisto-0.4.1.dist-info/RECORD
