Metadata-Version: 2.3
Name: hakisto
Version: 0.4.1
Summary: Logging re-imagined
License: LGPL-3.0-or-later
Keywords: logging
Author: Bernhard Radermacher
Author-email: bernhard.radermacher@netlink-consulting.com
Requires-Python: >=3.11,<4.0
Classifier: Development Status :: 4 - Beta
Classifier: Environment :: Console
Classifier: Intended Audience :: Developers
Classifier: License :: OSI Approved :: GNU Lesser General Public License v3 or later (LGPLv3+)
Classifier: Programming Language :: Python :: 3.11
Classifier: Programming Language :: Python :: 3.12
Classifier: Programming Language :: Python :: 3.13
Classifier: Topic :: Software Development
Classifier: Topic :: Utilities
Classifier: Typing :: Typed
Project-URL: Documentation, https://hakisto.readthedocs.io/
Project-URL: Repository, https://gitlab.com/hakisto-py/logger
